CHANGELOG.txt
LICENCE.txt
MANIFEST.in
README.txt
setup.py
easyConnectors/__init__.py
easyConnectors.egg-info/PKG-INFO
easyConnectors.egg-info/SOURCES.txt
easyConnectors.egg-info/dependency_links.txt
easyConnectors.egg-info/requires.txt
easyConnectors.egg-info/top_level.txt